{
  "HasRoutedMultipleMessage": true,
  "Messages": {
    "ServerProfiler_RequestNames": 17,
    "ScheduleUpdateRequest": 18,
    "LocalProximityAbilitySuccess": 19,
    "RemoteProximityAbilitySuccess": 20,
    "TrailRequest": 21,
    "RequestLeaveZone": 22,
    "RequestEncounterInfo": 23,
    "VotekickRequest": 24,
    "VotekickResponse": 25,
    "VotekickInitiated": 26,
    "VotekickResponded": 27,
    "ScoreBoardEnable": 28,
    "ScoreBoardInit": 29,
    "ScoreBoardSetWinner": 30,
    "ScoreBoardClear": 31,
    "ScoreBoardAddPlayer": 32,
    "ScoreBoardRemovePlayer": 33,
    "ScoreBoardUpdatePlayerStats": 34,
    "ScoreBoardUpdatePlayerStatus": 35,
    "ScoreBoardOnCharacterLoaded": 36,
    "MatchEndAck": 37,
    "ServerProfiler_SendNames": 38,
    "ServerProfiler_SendFrame": 39,
    "TempConsoleMessage": 40,
    "ReloadStaticData": 41,
    "EncDebugChatMessage": 42,
    "SendRadioMessage": 43,
    "NpcMonitoringLog": 44,
    "NpcNavigationInfo": 45,
    "NpcVoxelInfo": 46,
    "NpcDevCmdResponse": 47,
    "SquadVitalsUpdate": 48,
    "DevRequestObjectPositions": 49,
    "DevRequestSpawnTables": 50,
    "MissionObjectiveUpdated": 51,
    "MissionStatusChanged": 52,
    "MissionReturnToChanged": 53,
    "MissionsAvailable": 54,
    "Achievements": 55,
    "AchievementUnlocked": 56,
    "TotalAchievementPoints": 57,
    "AchievementCompletionCounts": 58,
    "ContentUnlocked": 59,
    "ClientUIAction": 60,
    "TrackRecipe": 61,
    "ClearTrackedRecipe": 62,
    "SlotTech": 63,
    "InteractableStatusChanged": 64,
    "SendTipMessage": 65,
    "SendLocalizedTipMessage": 66,
    "DebugLagPlayerSample": 67,
    "DebugLagSimulationSample": 68,
    "DebugLagRaiaSample": 69,
    "DebugEncounterVolumes": 70,
    "Trail": 71,
    "EncounterDebugNotification": 72,
    "EncounterUIScopeIn": 73,
    "EncounterUIUpdate": 74,
    "EncounterUIScopeOut": 75,
    "DisplayUiNotification": 76,
    "SetPreloadPosition": 77,
    "PlaySoundRecord": 78,
    "PlaySoundRecordAtLocation": 79,
    "PlayDialogScriptMessage": 80,
    "EncounterPublicInfo": 81,
    "ShoppingListInit": 82,
    "SetClientDailyInfo": 83
  },
  "Children": {
    "Character": {
      "Views": {
        "BaseController": 2,
        "NPCController": 3,
        "MissionAndMarkerController": 4,
        "CombatController": 5,
        "SpectatorController": 6,
        "ObserverView": 7,
        "EquipmentView": 8,
        "AIObserverView": 9,
        "CombatView": 10,
        "MovementView": 11,
        "TinyObjectView": 12,
        "DynamicProjectileView": 13
      },
      "Messages": {
        "ListItemComplete": 70,
        "ReceiveWeaponTweaks": 71,
        "TookDebugWeaponHitPublic": 72,
        "TookDebugWeaponHit": 73,
        "DebugWeaponStats": 74,
        "RewardInfo": 75,
        "ProgressionXpRefresh": 76,
        "ReceivedDeferredXP": 77,
        "PublicCombatLog": 78,
        "PrivateCombatLog": 79,
        "AnimationUpdated": 80,
        "RaiaNPCDebugging": 81,
        "WeaponProjectileFired": 82,
        "AbilityProjectileFired": 83,
        "ProjectileHitReported": 84,
        "Stumble": 85,
        "QuickChat": 86,
        "ProximityTextChat": 87,
        "JumpActioned": 88,
        "JumpRolled": 89,
        "Respawned": 90,
        "CalledForHelp": 91,
        "TookHit": 92,
        "AlmostHit": 93,
        "DealtHit": 94,
        "Killed": 95,
        "WarnLockTargeted": 96,
        "CurrentPoseUpdate": 97,
        "ConfirmedPoseUpdate": 98,
        "PublicDebugMovementUpdate": 99,
        "ForcedMovement": 100,
        "ForcedMovementCancelled": 101,
        "GrappleClimbPermission": 102,
        "AbilityActivated": 103,
        "AbilityFailed": 104,
        "AbilityCooldowns": 105,
        "NPCInteraction": 106,
        "OpenMovieDialog": 107,
        "PrivateDialog": 108,
        "PublicDialog": 109,
        "AddOrUpdateInteractives": 110,
        "RemoveInteractives": 111,
        "InteractionProgressed": 112,
        "InteractionCompleted": 113,
        "InteractedWithProgressed": 114,
        "InteractedWithCompleted": 115,
        "InventoryUpdate": 116,
        "SimulateLootPickup": 117,
        "DisplayRewards": 118,
        "VehicleConfigurationUpdate": 119,
        "TrackerEvent": 120,
        "TrackerPulse": 121,
        "PriorityTargetSet": 122,
        "ResourceNodeCompletedEvent": 123,
        "FoundResourceAreas": 124,
        "GeographicalReportResponse": 125,
        "ResourceLocationInfosResponse": 126,
        "UiNamedVariableUpdate": 127,
        "DuelNotification": 128,
        "NewUiQuery": 129,
        "UiQueryCancelled": 130,
        "MatchQueueResponse": 131,
        "ChallengeCreateResponse": 132,
        "CharacterLoaded": 133,
        "VendorTokenMachineResponse": 134,
        "UnlockContentSuccess": 135,
        "PushBehavior": 136,
        "PopBehavior": 137,
        "SelfReviveResponse": 138,
        "ApplyCameraShake": 139,
        "ReceivedWebUIMessage": 140
      },
      "Commands": {
        "UiQueryResponse": 58,
        "ListItemForSale": 70,
        "ToggleMarketplace": 71,
        "RequestLogout": 72,
        "JoinSquadLeader": 73,
        "PlayerReady": 74,
        "MatchQueue": 75,
        "MatchAccept": 76,
        "ChallengeCreate": 77,
        "ChallengeLeave": 78,
        "ChallengeInvitation": 79,
        "ChallengeInvitationResponse": 80,
        "ChallengeInvitationSquadInfo": 81,
        "ChallengeKick": 82,
        "ChallengeSetReady": 83,
        "ChallengeReadyCheck": 84,
        "ChallengeSwapTeam": 85,
        "ChallengeSetRoleAndTeam": 86,
        "ChallengeSetMatchParameters": 87,
        "ChallengeSetPowerPrivilege": 88,
        "ChallengeStartMatch": 89,
        "MapOpened": 90,
        "BattleframePurchased": 91,
        "PlayerRequestsDestroyItem": 92,
        "PlayerRequestsDestroyResource": 93,
        "CollectLoot": 94,
        "TempSlotAbilities": 95,
        "SinAcquire_Source": 96,
        "BroadcastWeaponTweaks": 97,
        "MovementInput": 98,
        "MovementInputFake": 99,
        "FireInputIgnored": 100,
        "FireBurst": 101,
        "FireEnd": 102,
        "FireCancel": 103,
        "FireWeaponProjectile": 104,
        "ReportProjectileHit": 105,
        "SelectFireMode": 106,
        "UseScope": 107,
        "SelectWeapon": 108,
        "ReloadWeapon": 109,
        "CancelReload": 110,
        "AcquireWeaponTarget": 111,
        "LoseWeaponTarget": 112,
        "NPCApplyEffect": 113,
        "NPCRemoveEffect": 114,
        "DockToPlayer": 115,
        "ChangeLookAtTarget": 116,
        "ActivateAbility": 117,
        "NPCInteractWithTarget": 118,
        "TargetAbility": 119,
        "DeactivateAbility": 120,
        "ActivateConsumable": 121,
        "ExitAttachmentRequest": 122,
        "NPCSetInteractionType": 123,
        "PerformEmote": 124,
        "NotifyDialogScriptComplete": 125,
        "PerformQuickChatCommand": 126,
        "PerformProximityTextChat": 127,
        "PerformDialog": 128,
        "SetDialogTag": 129,
        "SetEffectsFlag": 130,
        "AnimationUpdate": 131,
        "SelectLoadout": 132,
        "EditVehicleConfiguration": 133,
        "CallForHelp": 134,
        "ActivateMission": 135,
        "DebugMission": 136,
        "ListAchievements": 137,
        "RequestAchievementStatus": 138,
        "RequestAllAchievements": 139,
        "RequestMissionAvailability": 140,
        "RequestNewActivity": 141,
        "RequestPushMission": 142,
        "LogDirectActivityRequest": 143,
        "LogActivityPush": 144,
        "LogLongTimeWithoutPush": 145,
        "CameraPoseUpdate": 146,
        "QueueUnstuck": 147,
        "VehicleCalldownRequest": 148,
        "DeployableCalldownRequest": 149,
        "DeployableHardpointSelection": 150,
        "ResourceNodeBeaconCalldownRequest": 151,
        "ImmediateDespawn": 152,
        "FindNearbyResourceAreas": 153,
        "GeographicalReportRequest": 154,
        "SetSquadMembers": 155,
        "ClientQueryInteractionStatus": 156,
        "ResourceLocationInfosRequest": 157,
        "DuelRequest": 158,
        "PickupCarryableObjectByProximity": 159,
        "DropCarryableObject": 160,
        "AiError": 161,
        "AiSignal": 162,
        "NonDevDebugCommand": 163,
        "UpdateShoppingList": 164,
        "FindServiceProvider": 165,
        "ClientUIEvent": 166,
        "SetMovementSimulation": 167,
        "RequestRespawn": 168,
        "RequestTransfer": 169,
        "VendorTokenMachineRequest": 170,
        "RequestSelfRevive": 171,
        "LeaveEncounterParty": 172
      }
    },
    "Melding": {
      "Views": {
        "ObserverView": 15
      }
    },
    "MeldingBubble": {
      "Views": {
        "ObserverView": 17
      }
    },
    "AreaVisualData": {
      "Views": {
        "ObserverView": 19,
        "ParticleEffectsView": 20,
        "MapMarkerView": 21,
        "TinyObjectView": 22,
        "LootObjectView": 23,
        "ForceShieldView": 24
      },
      "Messages": {
        "LootObjectCollected": 70,
        "AudioEmitterSpawned": 71
      }
    },
    "Vehicle": {
      "Views": {
        "BaseController": 26,
        "CombatController": 27,
        "ObserverView": 28,
        "CombatView": 29,
        "MovementView": 30
      },
      "Messages": {
        "AbilityActivated": 70,
        "AbilityFailed": 71,
        "WeaponProjectileFired": 72,
        "PublicCombatLog": 73,
        "CurrentPoseUpdate": 74
      },
      "Commands": {
        "MovementInput": 70,
        "MovementInputFake": 71,
        "SinAcquire_Source": 72,
        "ReceiveCollisionDamage": 73,
        "ActivateAbility": 74,
        "DeactivateAbility": 75,
        "FireBurst": 76,
        "FireEnd": 77,
        "FireWeaponProjectile": 78,
        "SetWaterLevelAndDesc": 79,
        "SetEffectsFlag": 80
      }
    },
    "Anchor": {
      "Views": {
        "AIObserverView": 32
      }
    },
    "Deployable": {
      "Views": {
        "ObserverView": 34,
        "NPCObserverView": 35,
        "HardpointView": 36
      },
      "Messages": {
        "TookHit": 70,
        "AbilityProjectileFired": 71,
        "PublicCombatLog": 72
      }
    },
    "Turret": {
      "Views": {
        "BaseController": 38,
        "ObserverView": 39
      },
      "Messages": {
        "WeaponProjectileFired": 70
      },
      "Commands": {
        "PoseUpdate": 70,
        "FireBurst": 71,
        "FireEnd": 72,
        "FireWeaponProjectile": 73
      }
    },
    "Outpost": {
      "Views": {
        "ObserverView": 44
      }
    },
    "ResourceNode": {
      "Views": {
        "ObserverView": 47
      }
    },
    "CarryableObject": {
      "Views": {
        "ObserverView": 50
      }
    },
    "LootStoreExtension": {
      "Views": {
        "LootObjectView": 52
      },
      "Messages": {
        "LootObjectCollected": 70
      }
    },
    "Encounter": {
      "Commands": {
        "UiQueryResponse": 58
      }
    }
  }
}